textdistance/__init__.py
textdistance/benchmark.py
textdistance/libraries.json
textdistance/libraries.py
textdistance/py.typed
textdistance/utils.py
textdistance/algorithms/__init__.py
textdistance/algorithms/base.py
textdistance/algorithms/compression_based.py
textdistance/algorithms/edit_based.py
textdistance/algorithms/phonetic.py
textdistance/algorithms/sequence_based.py
textdistance/algorithms/simple.py
textdistance/algorithms/token_based.py
textdistance/algorithms/types.py
textdistance/algorithms/vector_based.py
textdistance-4.6.3.dist-info/LICENSE
textdistance-4.6.3.dist-info/METADATA
textdistance-4.6.3.dist-info/WHEEL
textdistance-4.6.3.dist-info/top_level.txt
textdistance-4.6.3.dist-info/RECORD
