Metadata-Version: 2.1
Name: textdistance
Version: 4.6.3
Summary: Compute distance between the two texts.
Home-page: https://github.com/orsinium/textdistance
Download-URL: https://github.com/orsinium/textdistance/tarball/master
Author: orsinium
Author-email: gram@orsinium.dev
License: MIT
Keywords: distance between text strings sequences iterators
Classifier: Development Status :: 5 - Production/Stable
Classifier: Environment :: Plugins
Classifier: Intended Audience :: Developers
Classifier: License :: OSI Approved :: MIT License
Classifier: Programming Language :: Python
Classifier: Topic :: Scientific/Engineering :: Human Machine Interfaces
Requires-Python: >=3.5
License-File: LICENSE
Provides-Extra: extras
Requires-Dist: jellyfish; extra == "extras"
Requires-Dist: numpy; extra == "extras"
Requires-Dist: Levenshtein; extra == "extras"
Requires-Dist: pyxDamerauLevenshtein; extra == "extras"
Requires-Dist: rapidfuzz>=2.6.0; extra == "extras"
Provides-Extra: benchmark
Requires-Dist: jellyfish; extra == "benchmark"
Requires-Dist: numpy; extra == "benchmark"
Requires-Dist: Levenshtein; extra == "benchmark"
Requires-Dist: pyxDamerauLevenshtein; extra == "benchmark"
Requires-Dist: rapidfuzz>=2.6.0; extra == "benchmark"
Requires-Dist: distance; extra == "benchmark"
Requires-Dist: pylev; extra == "benchmark"
Requires-Dist: py_stringmatching; extra == "benchmark"
Requires-Dist: tabulate; extra == "benchmark"
Provides-Extra: test
Requires-Dist: hypothesis; extra == "test"
Requires-Dist: isort; extra == "test"
Requires-Dist: numpy; extra == "test"
Requires-Dist: pytest; extra == "test"
Provides-Extra: lint
Requires-Dist: twine; extra == "lint"
Requires-Dist: mypy; extra == "lint"
Requires-Dist: isort; extra == "lint"
Requires-Dist: flake8; extra == "lint"
Requires-Dist: types-tabulate; extra == "lint"
Requires-Dist: flake8-blind-except; extra == "lint"
Requires-Dist: flake8-bugbear; extra == "lint"
Requires-Dist: flake8-commas; extra == "lint"
Requires-Dist: flake8-logging-format; extra == "lint"
Requires-Dist: flake8-mutable; extra == "lint"
Requires-Dist: flake8-pep3101; extra == "lint"
Requires-Dist: flake8-quotes; extra == "lint"
Requires-Dist: flake8-string-format; extra == "lint"
Requires-Dist: flake8-tidy-imports; extra == "lint"
Requires-Dist: pep8-naming; extra == "lint"
Provides-Extra: dameraulevenshtein
Requires-Dist: rapidfuzz>=2.6.0; extra == "dameraulevenshtein"
Requires-Dist: jellyfish; extra == "dameraulevenshtein"
Requires-Dist: pyxDamerauLevenshtein; extra == "dameraulevenshtein"
Provides-Extra: hamming
Requires-Dist: Levenshtein; extra == "hamming"
Requires-Dist: rapidfuzz>=2.6.0; extra == "hamming"
Requires-Dist: jellyfish; extra == "hamming"
Requires-Dist: distance; extra == "hamming"
Provides-Extra: jaro
Requires-Dist: rapidfuzz>=2.6.0; extra == "jaro"
Requires-Dist: Levenshtein; extra == "jaro"
Provides-Extra: jarowinkler
Requires-Dist: rapidfuzz>=2.6.0; extra == "jarowinkler"
Requires-Dist: jellyfish; extra == "jarowinkler"
Provides-Extra: levenshtein
Requires-Dist: rapidfuzz>=2.6.0; extra == "levenshtein"
Requires-Dist: Levenshtein; extra == "levenshtein"
Provides-Extra: common
Requires-Dist: jellyfish; extra == "common"
Requires-Dist: numpy; extra == "common"
Requires-Dist: Levenshtein; extra == "common"
Requires-Dist: pyxDamerauLevenshtein; extra == "common"
Requires-Dist: rapidfuzz>=2.6.0; extra == "common"
Provides-Extra: all
Requires-Dist: jellyfish; extra == "all"
Requires-Dist: numpy; extra == "all"
Requires-Dist: Levenshtein; extra == "all"
Requires-Dist: pyxDamerauLevenshtein; extra == "all"
Requires-Dist: rapidfuzz>=2.6.0; extra == "all"
Requires-Dist: distance; extra == "all"
Requires-Dist: pylev; extra == "all"
Requires-Dist: py_stringmatching; extra == "all"
Requires-Dist: tabulate; extra == "all"
Provides-Extra: extra
Requires-Dist: jellyfish; extra == "extra"
Requires-Dist: numpy; extra == "extra"
Requires-Dist: Levenshtein; extra == "extra"
Requires-Dist: pyxDamerauLevenshtein; extra == "extra"
Requires-Dist: rapidfuzz>=2.6.0; extra == "extra"
Provides-Extra: benchmarks
Requires-Dist: jellyfish; extra == "benchmarks"
Requires-Dist: numpy; extra == "benchmarks"
Requires-Dist: Levenshtein; extra == "benchmarks"
Requires-Dist: pyxDamerauLevenshtein; extra == "benchmarks"
Requires-Dist: rapidfuzz>=2.6.0; extra == "benchmarks"
Requires-Dist: distance; extra == "benchmarks"
Requires-Dist: pylev; extra == "benchmarks"
Requires-Dist: py_stringmatching; extra == "benchmarks"
Requires-Dist: tabulate; extra == "benchmarks"
